sqlint/__init__.py
sqlint/__main__.py
sqlint/cli.py
sqlint/syntax_tree.py
sqlint/checker/__init__.py
sqlint/checker/base.py
sqlint/checker/checker.py
sqlint/checker/violation.py
sqlint/config/__init__.py
sqlint/config/config_loader.py
sqlint/config/default.ini
sqlint/formatter/__init__.py
sqlint/formatter/base.py
sqlint/formatter/formatter.py
sqlint/formatter/splitter.py
sqlint/parser/__init__.py
sqlint/parser/base.py
sqlint/parser/keywords.py
sqlint/parser/pattern.py
sqlint/parser/token.py
sqlint-0.2.4.dist-info/LICENCE
sqlint-0.2.4.dist-info/METADATA
sqlint-0.2.4.dist-info/WHEEL
sqlint-0.2.4.dist-info/entry_points.txt
sqlint-0.2.4.dist-info/top_level.txt
sqlint-0.2.4.dist-info/RECORD
