Metadata-Version: 2.1
Name: sqlint
Version: 0.2.4
Summary: Simple Sql Linter
Home-page: https://github.com/shigeru0215/sqlint
Author: shigeru0215
Author-email: matsuzaki215@gmail.com
License: MIT
Platform: UNKNOWN
Classifier: Development Status :: 3 - Alpha
Classifier: Environment :: Console
Classifier: Intended Audience :: Developers
Classifier: License :: OSI Approved :: MIT License
Classifier: Programming Language :: Python
Classifier: Programming Language :: Python :: 3
Classifier: Programming Language :: Python :: 3.6
Classifier: Programming Language :: Python :: 3.7
Classifier: Topic :: Software Development :: Quality Assurance
Classifier: Topic :: Text Processing :: General
Requires-Dist: click (==7.0)
Requires-Dist: configparser (==4.0.2)
